odoo/addons/account_payment_term_extension/README.rst
odoo/addons/account_payment_term_extension/__init__.py
odoo/addons/account_payment_term_extension/__manifest__.py
odoo/addons/account_payment_term_extension/demo/account_demo.xml
odoo/addons/account_payment_term_extension/documentation/DOC_payment_terms_rounding.ods
odoo/addons/account_payment_term_extension/i18n/account_payment_term_extension.pot
odoo/addons/account_payment_term_extension/i18n/am.po
odoo/addons/account_payment_term_extension/i18n/ar.po
odoo/addons/account_payment_term_extension/i18n/bg.po
odoo/addons/account_payment_term_extension/i18n/bs.po
odoo/addons/account_payment_term_extension/i18n/ca.po
odoo/addons/account_payment_term_extension/i18n/cs.po
odoo/addons/account_payment_term_extension/i18n/da.po
odoo/addons/account_payment_term_extension/i18n/de.po
odoo/addons/account_payment_term_extension/i18n/el_GR.po
odoo/addons/account_payment_term_extension/i18n/en_GB.po
odoo/addons/account_payment_term_extension/i18n/es.po
odoo/addons/account_payment_term_extension/i18n/es_AR.po
odoo/addons/account_payment_term_extension/i18n/es_CL.po
odoo/addons/account_payment_term_extension/i18n/es_CO.po
odoo/addons/account_payment_term_extension/i18n/es_CR.po
odoo/addons/account_payment_term_extension/i18n/es_DO.po
odoo/addons/account_payment_term_extension/i18n/es_EC.po
odoo/addons/account_payment_term_extension/i18n/es_MX.po
odoo/addons/account_payment_term_extension/i18n/es_PE.po
odoo/addons/account_payment_term_extension/i18n/es_PY.po
odoo/addons/account_payment_term_extension/i18n/es_VE.po
odoo/addons/account_payment_term_extension/i18n/et.po
odoo/addons/account_payment_term_extension/i18n/eu.po
odoo/addons/account_payment_term_extension/i18n/fa.po
odoo/addons/account_payment_term_extension/i18n/fi.po
odoo/addons/account_payment_term_extension/i18n/fr.po
odoo/addons/account_payment_term_extension/i18n/fr_CA.po
odoo/addons/account_payment_term_extension/i18n/fr_CH.po
odoo13_addon_account_payment_term_extension-13.0.3.0.5.dist-info/METADATA
odoo13_addon_account_payment_term_extension-13.0.3.0.5.dist-info/WHEEL
odoo13_addon_account_payment_term_extension-13.0.3.0.5.dist-info/top_level.txt
odoo13_addon_account_payment_term_extension-13.0.3.0.5.dist-info/RECORD
