Metadata-Version: 2.1
Name: odoo13-addon-account-payment-term-extension
Version: 13.0.3.0.5
Summary: Adds rounding, months, weeks and multiple payment days properties on payment term lines
Home-page: https://github.com/OCA/account-payment
Author: Camptocamp,Tecnativa,Agile Business Group, Odoo Community Association (OCA)
Author-email: support@odoo-community.org
License: AGPL-3
Platform: UNKNOWN
Classifier: Programming Language :: Python
Classifier: Framework :: Odoo
Classifier: Framework :: Odoo :: 13.0
Classifier: License :: OSI Approved :: GNU Affero General Public License v3
Requires-Python: >=3.5
Requires-Dist: odoo (<13.1dev,>=13.0a)
